{
  "H10002": {
    "productName": "ACEITE ESENCIAL ARBOL DEL TE BIO",
    "isBio": true
  },
  "H10003": {
    "productName": "FINIQUITO BIO",
    "isBio": true
  },
  "H10004": {
    "productName": "FRESHQUITO BIO",
    "isBio": true
  },
  "H10202": {
    "productName": "GEL HIDRATANTE ALOE VERA Y ROSA MOSQUETA BIO",
    "isBio": true
  },
  "H10301": {
    "productName": "ENERCAP BIO-ECO",
    "isBio": true
  },
  "H10403": {
    "productName": "ROSA MOSQUETA BIO",
    "isBio": true
  },
  "H12009": {
    "productName": "GUMMIES PROBIOTICOS",
    "isBio": true
  },
  "H13103": {
    "productName": "DOLOCALM GEL BIO",
    "isBio": true
  },
  "H13104": {
    "productName": "DOLOCALM ROLL-ON BIO",
    "isBio": true
  },
  "H13105": {
    "productName": "CANNALDOL CBD CREAM BIO",
    "isBio": true
  },
  "H16001": {
    "productName": "ALOE VERA BIO",
    "isBio": true
  },
  "H16002": {
    "productName": "PROBIOTICS",
    "isBio": true
  },
  "H17002": {
    "productName": "GEL HIDRATANTE Y LUBRICANTE BIO",
    "isBio": true
  },
  "H17004": {
    "productName": "CREMA ANTIESTRIAS BIO",
    "isBio": true
  },
  "H17201": {
    "productName": "GEL HIGIENE INTIMA BIO",
    "isBio": true
  },
  "H21203": {
    "productName": "VENACOLD GEL BIO",
    "isBio": true
  },
  "H24203": {
    "productName": "CREMA REDUCTORA INTENSIVA BIO",
    "isBio": true
  },
  "H24303": {
    "productName": "CELULIT OIL BIO",
    "isBio": true
  }
}